README.rst
setup.py
confidence/__init__.py
confidence/apps.py
confidence/tests.py
confidence/base/__init__.py
confidence/base/config.py
confidence/management/__init__.py
confidence/management/commands/__init__.py
confidence/management/commands/checkconf.py
confidence/management/commands/makeconf.py
confidence/migrations/__init__.py
confidence/presets/__init__.py
confidence/presets/generic.py
confidence/presets/library/__init__.py
confidence/presets/library/cache.py
confidence/presets/library/database.py
confidence/presets/library/email.py
django_confidence.egg-info/PKG-INFO
django_confidence.egg-info/SOURCES.txt
django_confidence.egg-info/dependency_links.txt
django_confidence.egg-info/top_level.txt