Metadata-Version: 1.1
Name: django-confidence
Version: 0.1.0
Summary: A Django app to manage project configuration files.
Home-page: https://volynov.ru/
Author: Mikhail volynov
Author-email: mikhail@volynov.ru
License: Apache 2.0 License
Platform: UNKNOWN
Classifier: Environment :: Web Environment
Classifier: Framework :: Django
Classifier: Framework :: Django :: 2.0
Classifier: Intended Audience :: Developers
Classifier: License :: OSI Approved :: Apache Software License
Classifier: Operating System :: OS Independent
Classifier: Programming Language :: Python
Classifier: Programming Language :: Python :: 3.5
Classifier: Programming Language :: Python :: 3.6
Classifier: Topic :: Internet :: WWW/HTTP
Classifier: Topic :: Internet :: WWW/HTTP :: Dynamic Content
